qbrick_alias/__init__.py
qbrick_alias/classes.py
qbrick_alias/manager.py
qbrick_alias-1.1.1.dist-info/METADATA
qbrick_alias-1.1.1.dist-info/WHEEL
qbrick_alias-1.1.1.dist-info/RECORD
