Metadata-Version: 2.3
Name: qbrick-alias
Version: 1.1.1
Summary: Path Alias Manager
Author: Alexey Volkov
Author-email: webwizardry@hotmail.com
Requires-Python: >=3.12
Classifier: Programming Language :: Python :: 3
Classifier: Programming Language :: Python :: 3.12
Classifier: Programming Language :: Python :: 3.13
